luxor_openapi_asyncio/__init__.py
luxor_openapi_asyncio/api_client.py
luxor_openapi_asyncio/configuration.py
luxor_openapi_asyncio/exceptions.py
luxor_openapi_asyncio/model_utils.py
luxor_openapi_asyncio/rest.py
luxor_openapi_asyncio/api/__init__.py
luxor_openapi_asyncio/api/controller_api.py
luxor_openapi_asyncio/api/groups_api.py
luxor_openapi_asyncio/api/lights_api.py
luxor_openapi_asyncio/api/themes_api.py
luxor_openapi_asyncio/apis/__init__.py
luxor_openapi_asyncio/model/__init__.py
luxor_openapi_asyncio/model/assign_light_request.py
luxor_openapi_asyncio/model/assign_light_response.py
luxor_openapi_asyncio/model/controller_name_response.py
luxor_openapi_asyncio/model/extinguish_all_response.py
luxor_openapi_asyncio/model/flash_lights_request.py
luxor_openapi_asyncio/model/flash_lights_response.py
luxor_openapi_asyncio/model/group.py
luxor_openapi_asyncio/model/group_list_add_request.py
luxor_openapi_asyncio/model/group_list_add_response.py
luxor_openapi_asyncio/model/group_list_clear_response.py
luxor_openapi_asyncio/model/group_list_delete_request.py
luxor_openapi_asyncio/model/group_list_delete_response.py
luxor_openapi_asyncio/model/group_list_get_response.py
luxor_openapi_asyncio/model/group_list_rename_request.py
luxor_openapi_asyncio/model/group_list_rename_response.py
luxor_openapi_asyncio/model/group_list_reorder_request.py
luxor_openapi_asyncio/model/group_list_reorder_response.py
luxor_openapi_asyncio/model/illuminate_all_response.py
luxor_openapi_asyncio/model/illuminate_group_request.py
luxor_openapi_asyncio/model/illuminate_group_response.py
luxor_openapi_asyncio/model/illuminate_theme_request.py
luxor_openapi_asyncio/model/illuminate_theme_response.py
luxor_openapi_asyncio/model/theme.py
luxor_openapi_asyncio/model/theme_clear_request.py
luxor_openapi_asyncio/model/theme_clear_response.py
luxor_openapi_asyncio/model/theme_get_request.py
luxor_openapi_asyncio/model/theme_get_response.py
luxor_openapi_asyncio/model/theme_group.py
luxor_openapi_asyncio-0.1.0.dist-info/METADATA
luxor_openapi_asyncio-0.1.0.dist-info/WHEEL
luxor_openapi_asyncio-0.1.0.dist-info/top_level.txt
luxor_openapi_asyncio-0.1.0.dist-info/RECORD
