Metadata-Version: 2.1
Name: luxor-openapi-asyncio
Version: 0.1.0
Summary: FXLuminaire Luxor
Home-page: UNKNOWN
Author: OpenAPI Generator community
Author-email: team@openapitools.org
License: Apache 2.0
Keywords: OpenAPI,OpenAPI-Generator,FXLuminaire Luxor
Platform: UNKNOWN
Requires-Dist: urllib3 (>=1.25.3)
Requires-Dist: six (>=1.10)
Requires-Dist: python-dateutil
Requires-Dist: aiohttp (>=3.0.0)
